pyhampel/__init__.py
pyhampel/__main__.py
pyhampel/dataviz/__init__.py
pyhampel/dataviz/interactive_viz.py
pyhampel/ingestion/__init__.py
pyhampel/ingestion/time_series_ingestion.py
pyhampel/src/HampelFiltering.py
pyhampel/src/HampelFilteringWithDev.py
pyhampel/src/HampelWithDev.py
pyhampel/src/__init__.py
pyhampel/src/filtering.py
pyhampel/src/filtering_with_dev.py
pyhampel/src/multiproc_filtering.py
pyhampel/src/multiproc_filtering_w_dev.py
pyhampel/utils/__init__.py
pyhampel/utils/ts_utils.py
pyhampel-0.3.7.dist-info/LICENSE
pyhampel-0.3.7.dist-info/METADATA
pyhampel-0.3.7.dist-info/WHEEL
pyhampel-0.3.7.dist-info/top_level.txt
pyhampel-0.3.7.dist-info/RECORD
